ernwin-1.3.0.data/scripts/ernwin.py
ernwin-1.3.0.data/scripts/plot_ernwin_pdd.py
ernwin-1.3.0.data/scripts/reconstruct.py
fess/SortedCollection.py
fess/__init__.py
fess/directory_utils.py
fess/utils.py
fess/builder/__init__.py
fess/builder/_commandline_helper.py
fess/builder/_other_movers.py
fess/builder/aminor.py
fess/builder/builder.py
fess/builder/ccd.py
fess/builder/config.py
fess/builder/create.py
fess/builder/energy.py
fess/builder/energy_abcs.py
fess/builder/models.py
fess/builder/monitor.py
fess/builder/move.py
fess/builder/reconstructor.py
fess/builder/relaxation_builder.py
fess/builder/replicaExchange.py
fess/builder/sampling.py
fess/builder/stat_container.py
fess/ccd/__init__.py
fess/ccd/ccd.py
fess/ccd/rotation_matrix_test.py
fess/ccd/setup.py
fess/motif/__init__.py
fess/motif/annotate.py
fess/motif/motif_atlas.py
fess/stats/AME_distributions.csv
fess/stats/all_nr3.36.stats
fess/stats/cde_reference_dist_nr2.110.csv
fess/stats/cylinder_intersections_loop_rog.csv
fess/stats/cylinder_intersections_native.csv
fess/stats/residue_template.pdb
fess/stats/rog_reference_dist_1S72_0.csv
fess/stats/rog_reference_dist_nr2.110.csv
fess/stats/rog_target_dist_1S72_0.csv
fess/stats/rog_target_dist_nr2.110.csv
fess/stats/sld_reference_dist_1S72_0.csv
fess/stats/sld_reference_dist_nr2.110.csv
fess/stats/sld_target_dist_1S72_0.csv
fess/stats/sld_target_dist_nr2.110.csv
ernwin-1.3.0.dist-info/LICENSE
ernwin-1.3.0.dist-info/METADATA
ernwin-1.3.0.dist-info/WHEEL
ernwin-1.3.0.dist-info/top_level.txt
ernwin-1.3.0.dist-info/RECORD
