Metadata-Version: 2.1
Name: ernwin
Version: 1.3.0
Summary: Coarse Grain 3D RNA Structure Modelling
Home-page: http://www.tbi.univie.ac.at/~thiel/ernwin/
Author: Bernhard Thiel, Peter Kerpedjiev
Author-email: thiel@tbi.univie.ac.at, pkerp@tbi.univie.ac.at
License-File: LICENSE
Requires-Dist: pandas >=0.19
Requires-Dist: numpy
Requires-Dist: scipy
Requires-Dist: biopython
Requires-Dist: deepdiff
Requires-Dist: networkx
Requires-Dist: future
Requires-Dist: forgi >=2.2.1
Requires-Dist: logging-exceptions
Requires-Dist: commandline-parsable >=0.2
Requires-Dist: scikit-learn
Requires-Dist: matplotlib
Requires-Dist: contextlib2
Requires-Dist: bitarray
